fiddler/__init__.py
fiddler/cli.py
fiddler/cli_utils.py
fiddler/clone_cmd.py
fiddler/dataset_yaml_generator.py
fiddler/execute_cmd.py
fiddler/explain_cmd.py
fiddler/import_cmd.py
fiddler/sagemaker_endpoint_cmd.py
fiddler_cli-0.2.3.1.dist-info/LICENSE.txt
fiddler_cli-0.2.3.1.dist-info/METADATA
fiddler_cli-0.2.3.1.dist-info/WHEEL
fiddler_cli-0.2.3.1.dist-info/entry_points.txt
fiddler_cli-0.2.3.1.dist-info/top_level.txt
fiddler_cli-0.2.3.1.dist-info/RECORD
