Metadata-Version: 2.1
Name: fiddler-cli
Version: 0.2.3.1
Summary: CLI and tools for interacting with Fiddler Service
Home-page: https://fiddler.ai
Author: Fiddler Labs
Author-email: dev@fiddler.ai
License: UNKNOWN
Platform: UNKNOWN
Classifier: Programming Language :: Python :: 3
Classifier: Operating System :: OS Independent
Requires-Dist: boto3
Requires-Dist: pandas (>=0.2)
Requires-Dist: pyyaml
Requires-Dist: requests
